sbvoicedb/__init__.py
sbvoicedb/database.py
sbvoicedb/download.py
sbvoicedb/utils.py
sbvoicedb/qt/SbVoiceDbTreeModel.py
sbvoicedb/qt/SbVoiceDbTreeWidget.py
sbvoicedb/qt/SummaryTableModels.py
sbvoicedb/qt/SummaryTableWidgets.py
sbvoicedb/qt/__init.__.py
sbvoicedb-0.4.0.dist-info/licenses/LICENSE
sbvoicedb-0.4.0.dist-info/METADATA
sbvoicedb-0.4.0.dist-info/WHEEL
sbvoicedb-0.4.0.dist-info/top_level.txt
sbvoicedb-0.4.0.dist-info/RECORD
