Metadata-Version: 2.4
Name: sbvoicedb
Version: 0.4.0
Summary: Saarbrueken Voice Database Downloader and Reader
License: GPL-2.0 License
Project-URL: Repository, https://github.com/tikuma-lsuhsc/python-sbvoicedb
Project-URL: Issues, https://github.com/tikuma-lsuhsc/python-sbvoicedb/issues
Project-URL: Pull_Requests, https://github.com/tikuma-lsuhsc/python-sbvoicedb/pulls
Keywords: multimedia
Classifier: Development Status :: 4 - Beta
Classifier: License :: OSI Approved :: GNU General Public License v2 (GPLv2)
Classifier: Topic :: Multimedia :: Sound/Audio
Classifier: Programming Language :: Python :: 3
Requires-Python: >=3.10
License-File: LICENSE
Requires-Dist: numpy
Requires-Dist: requests
Requires-Dist: tqdm
Requires-Dist: nspfile>=0.2.0
Requires-Dist: sqlalchemy>=2.0.0
Requires-Dist: typing_extensions
Requires-Dist: platformdirs
Provides-Extra: qt
Requires-Dist: qtpy; extra == "qt"
Dynamic: license-file
